{
    "id": "example_panel",
    "root": {
        "type": "window",
        "props": {
            "title": "FastRenderer 示例面板",
            "width": 400,
            "height": 300
        },
        "children": [
            {
                "type": "text",
                "props": {
                    "value": "欢迎使用 FastRenderer！",
                    "color": "#FFD700"
                }
            },
            {
                "type": "button",
                "props": {
                    "text": "点击",
                    "onClick": "example_click",
                    "color": "#3D85E0"
                }
            }
        ]
    }
}
